[
  {
    "ID":0,
    "Name":"Application is not rendering in Internet Explorer 8",
    "Description":"Application is not rendering in Internet Explorer 8; please help",
    "Created":"\/Date(694224000000)\/",
    "Priority":1,
    "Owner":"John Doe",
    "Status": "New"
  },
  {
    "ID":1,
    "Name":"Please implement versioning of issues.",
    "Description":"Please implement versioning of issues. I want to track changes made, and possibly revert to previous versions",
    "Created":"\/Date(694224003001)\/",
    "Priority":2,
    "Owner":"Mary Jane",
    "Status": "In Progress"
  }
]